dear_assistant/__about__.py
dear_assistant/__init__.py
dear_assistant/__main__.py
dear_assistant-0.0.1.dist-info/METADATA
dear_assistant-0.0.1.dist-info/WHEEL
dear_assistant-0.0.1.dist-info/entry_points.txt
dear_assistant-0.0.1.dist-info/licenses/LICENSE
dear_assistant-0.0.1.dist-info/RECORD
